{"simple_name":"Recipe","source_file":"zombie/scripting/objects/Recipe.java","set_exposed":true,"lua_tagged":true,"is_enum":false,"methods":[{"name":"isRequiresWorkstation","return_type":"boolean","params":[],"lua_tagged":false},{"name":"getStationMultiplier","return_type":"float","params":[],"lua_tagged":false},{"name":"Load","return_type":"void","params":[{"type":"String","name":"name"},{"type":"String","name":"totalFile"}],"lua_tagged":false},{"name":"DoSource","return_type":"void","params":[{"type":"String","name":"type"}],"lua_tagged":false},{"name":"DoResult","return_type":"void","params":[{"type":"String","name":"type"}],"lua_tagged":false},{"name":"getNumberOfNeededItem","return_type":"int","params":[],"lua_tagged":false},{"name":"getRequiredSkills","return_type":"ArrayList<String>","params":[],"lua_tagged":false},{"name":"getRequiredSkillCount","return_type":"int","params":[],"lua_tagged":false},{"name":"getRequiredSkill","return_type":"RequiredSkill","params":[{"type":"int","name":"index"}],"lua_tagged":false},{"name":"clearRequiredSkills","return_type":"void","params":[],"lua_tagged":false},{"name":"addRequiredSkill","return_type":"void","params":[{"type":"PerkFactory.Perk","name":"perk"},{"type":"int","name":"level"}],"lua_tagged":false},{"name":"findSource","return_type":"Source","params":[{"type":"String","name":"sourceFullType"}],"lua_tagged":false},{"name":"getSource","return_type":"ArrayList<Source>","params":[],"lua_tagged":false},{"name":"getOriginalname","return_type":"String","params":[],"lua_tagged":false},{"name":"setOriginalname","return_type":"void","params":[{"type":"String","name":"originalname"}],"lua_tagged":false},{"name":"getFullType","return_type":"String","params":[],"lua_tagged":false},{"name":"getName","return_type":"String","params":[],"lua_tagged":false},{"name":"getHeat","return_type":"float","params":[],"lua_tagged":false},{"name":"getResult","return_type":"Result","params":[],"lua_tagged":false},{"name":"getNearItem","return_type":"String","params":[],"lua_tagged":false},{"name":"setNearItem","return_type":"void","params":[{"type":"String","name":"nearItem"}],"lua_tagged":false},{"name":"getResults","return_type":"ArrayList<Result>","params":[],"lua_tagged":false}],"fields":[{"name":"timeToMake","type":"float","lua_tagged":false},{"name":"sound","type":"String","lua_tagged":false},{"name":"source","type":"ArrayList<Source>","lua_tagged":false},{"name":"result","type":"Result","lua_tagged":false},{"name":"results","type":"ArrayList<Result>","lua_tagged":false},{"name":"allowDestroyedItem","type":"boolean","lua_tagged":false},{"name":"allowFrozenItem","type":"boolean","lua_tagged":false},{"name":"allowRottenItem","type":"boolean","lua_tagged":false},{"name":"allowOnlyOne","type":"boolean","lua_tagged":false},{"name":"inSameInventory","type":"boolean","lua_tagged":false},{"name":"name","type":"String","lua_tagged":false},{"name":"skillRequired","type":"ArrayList<RequiredSkill>","lua_tagged":false},{"name":"hidden","type":"boolean","lua_tagged":false}],"nested_types":[{"name":"Result","kind":"class","fqn":"zombie.scripting.objects.Recipe.Result"},{"name":"Source","kind":"class","fqn":"zombie.scripting.objects.Recipe.Source"},{"name":"RequiredSkill","kind":"class","fqn":"zombie.scripting.objects.Recipe.RequiredSkill"},{"name":"LuaCall","kind":"enum","fqn":"zombie.scripting.objects.Recipe.LuaCall"}],"extends":"zombie.scripting.objects.BaseScriptObject","subclasses":["zombie.scripting.objects.MovableRecipe"]}