{"simple_name":"Vector3","source_file":"zombie/iso/Vector3.java","set_exposed":true,"lua_tagged":true,"is_enum":false,"methods":[{"name":"rotate","return_type":"void","params":[{"type":"float","name":"rad"}],"lua_tagged":false},{"name":"rotatey","return_type":"void","params":[{"type":"float","name":"rad"}],"lua_tagged":false},{"name":"add","return_type":"Vector2","params":[{"type":"Vector2","name":"other"}],"lua_tagged":false},{"name":"addToThis","return_type":"Vector3","params":[{"type":"Vector2","name":"other"}],"lua_tagged":false},{"name":"addToThis","return_type":"Vector3","params":[{"type":"Vector3","name":"other"}],"lua_tagged":false},{"name":"div","return_type":"Vector3","params":[{"type":"float","name":"scalar"}],"lua_tagged":false},{"name":"aimAt","return_type":"Vector3","params":[{"type":"Vector2","name":"other"}],"lua_tagged":false},{"name":"angleTo","return_type":"float","params":[{"type":"Vector2","name":"other"}],"lua_tagged":false},{"name":"clone","return_type":"Vector3","params":[],"lua_tagged":false},{"name":"distanceTo","return_type":"float","params":[{"type":"Vector2","name":"other"}],"lua_tagged":false},{"name":"distanceTo","return_type":"float","params":[{"type":"Vector3","name":"other"}],"lua_tagged":false},{"name":"distanceTo","return_type":"float","params":[{"type":"float","name":"x"},{"type":"float","name":"y"},{"type":"float","name":"z"}],"lua_tagged":false},{"name":"dot","return_type":"float","params":[{"type":"Vector2","name":"other"}],"lua_tagged":false},{"name":"dot3d","return_type":"float","params":[{"type":"Vector3","name":"other"}],"lua_tagged":false},{"name":"equals","return_type":"boolean","params":[{"type":"Object","name":"other"}],"lua_tagged":false},{"name":"getDirection","return_type":"float","params":[],"lua_tagged":false},{"name":"setDirection","return_type":"Vector3","params":[{"type":"float","name":"direction"}],"lua_tagged":false},{"name":"getLength","return_type":"float","params":[],"lua_tagged":false},{"name":"getLengthSq","return_type":"float","params":[],"lua_tagged":false},{"name":"setLength","return_type":"Vector3","params":[{"type":"float","name":"length"}],"lua_tagged":false},{"name":"normalize","return_type":"void","params":[],"lua_tagged":false},{"name":"set","return_type":"Vector3","params":[{"type":"Vector3","name":"other"}],"lua_tagged":false},{"name":"set","return_type":"Vector3","params":[{"type":"float","name":"x"},{"type":"float","name":"y"},{"type":"float","name":"z"}],"lua_tagged":false},{"name":"setLengthAndDirection","return_type":"Vector3","params":[{"type":"float","name":"direction"},{"type":"float","name":"length"}],"lua_tagged":false},{"name":"toString","return_type":"String","params":[],"lua_tagged":false},{"name":"sub","return_type":"Vector3","params":[{"type":"Vector3","name":"val"},{"type":"Vector3","name":"out"}],"lua_tagged":false}],"fields":[{"name":"x","type":"float","lua_tagged":false},{"name":"y","type":"float","lua_tagged":false},{"name":"z","type":"float","lua_tagged":false}],"nested_types":[],"implements":["Cloneable"]}