{"simple_name":"ItemVisuals","source_file":"zombie/core/skinnedmodel/visual/ItemVisuals.java","set_exposed":true,"lua_tagged":true,"is_enum":false,"methods":[{"name":"save","return_type":"void","params":[{"type":"ByteBuffer","name":"output"}],"lua_tagged":false},{"name":"load","return_type":"void","params":[{"type":"ByteBuffer","name":"input"},{"type":"int","name":"worldVersion"}],"lua_tagged":false},{"name":"findHat","return_type":"ItemVisual","params":[],"lua_tagged":false},{"name":"findMask","return_type":"ItemVisual","params":[],"lua_tagged":false},{"name":"getDescription","return_type":"String","params":[],"lua_tagged":false}],"fields":[],"nested_types":[],"extends":"java.util.ArrayList"}