{"simple_name":"ActionProgressBar","source_file":"zombie/ui/ActionProgressBar.java","set_exposed":true,"lua_tagged":true,"is_enum":false,"methods":[{"name":"render","return_type":"void","params":[],"lua_tagged":false},{"name":"setValue","return_type":"void","params":[{"type":"float","name":"delta"}],"lua_tagged":false},{"name":"getValue","return_type":"float","params":[],"lua_tagged":false},{"name":"update","return_type":"void","params":[{"type":"int","name":"nPlayer"}],"lua_tagged":false}],"fields":[{"name":"delayHide","type":"int","lua_tagged":false}],"nested_types":[],"extends":"zombie.ui.UIElement"}