{"simple_name":"PhysicsShape","source_file":"zombie/scripting/objects/VehicleScript.java","set_exposed":true,"lua_tagged":true,"is_enum":false,"methods":[{"name":"getTypeString","return_type":"String","params":[],"lua_tagged":false},{"name":"getOffset","return_type":"Vector3f","params":[],"lua_tagged":false},{"name":"getExtents","return_type":"Vector3f","params":[],"lua_tagged":false},{"name":"getRotate","return_type":"Vector3f","params":[],"lua_tagged":false},{"name":"getRadius","return_type":"float","params":[],"lua_tagged":false},{"name":"setRadius","return_type":"void","params":[{"type":"float","name":"radius"}],"lua_tagged":false},{"name":"getPhysicsShapeScript","return_type":"String","params":[],"lua_tagged":false},{"name":"setPhysicsShapeScript","return_type":"void","params":[{"type":"String","name":"scriptId"}],"lua_tagged":false}],"fields":[{"name":"type","type":"int","lua_tagged":false},{"name":"offset","type":"Vector3f","lua_tagged":false},{"name":"rotate","type":"Vector3f","lua_tagged":false},{"name":"extents","type":"Vector3f","lua_tagged":false},{"name":"radius","type":"float","lua_tagged":false},{"name":"physicsShapeScript","type":"String","lua_tagged":false}],"nested_types":[]}