{"simple_name":"InputScript","source_file":"zombie/scripting/entity/components/crafting/InputScript.java","set_exposed":true,"lua_tagged":true,"is_enum":false,"methods":[{"name":"getPossibleInputItems","return_type":"List<Item>","params":[],"lua_tagged":false},{"name":"hasPossibleFrozenFoodInputItems","return_type":"boolean","params":[],"lua_tagged":false},{"name":"getPossibleInputFluids","return_type":"ArrayList<Fluid>","params":[],"lua_tagged":false},{"name":"getInputFluidFilterDisplayName","return_type":"String","params":[],"lua_tagged":false},{"name":"getInputFluidFilterTooltip","return_type":"String","params":[],"lua_tagged":false},{"name":"getPossibleInputEnergies","return_type":"ArrayList<Energy>","params":[],"lua_tagged":false},{"name":"hasCreateToItem","return_type":"boolean","params":[],"lua_tagged":false},{"name":"getCreateToItemScript","return_type":"OutputScript","params":[],"lua_tagged":false},{"name":"hasConsumeFromItem","return_type":"boolean","params":[],"lua_tagged":false},{"name":"getConsumeFromItemScript","return_type":"InputScript","params":[],"lua_tagged":false},{"name":"hasParentScript","return_type":"boolean","params":[],"lua_tagged":false},{"name":"getParentScript","return_type":"InputScript","params":[],"lua_tagged":false},{"name":"hasFlag","return_type":"boolean","params":[{"type":"InputFlag","name":"flag"}],"lua_tagged":false},{"name":"getOriginalLine","return_type":"String","params":[],"lua_tagged":false},{"name":"getResourceType","return_type":"ResourceType","params":[],"lua_tagged":false},{"name":"isUsesPartialItem","return_type":"boolean","params":[{"type":"Item","name":"item"}],"lua_tagged":false},{"name":"isExclusive","return_type":"boolean","params":[],"lua_tagged":false},{"name":"isItemCount","return_type":"boolean","params":[],"lua_tagged":false},{"name":"isDestroy","return_type":"boolean","params":[],"lua_tagged":false},{"name":"isKeep","return_type":"boolean","params":[],"lua_tagged":false},{"name":"isTool","return_type":"boolean","params":[],"lua_tagged":false},{"name":"isToolLeft","return_type":"boolean","params":[],"lua_tagged":false},{"name":"isToolRight","return_type":"boolean","params":[],"lua_tagged":false},{"name":"isWorn","return_type":"boolean","params":[],"lua_tagged":false},{"name":"isNotWorn","return_type":"boolean","params":[],"lua_tagged":false},{"name":"isFull","return_type":"boolean","params":[],"lua_tagged":false},{"name":"isEmpty","return_type":"boolean","params":[],"lua_tagged":false},{"name":"notFull","return_type":"boolean","params":[],"lua_tagged":false},{"name":"notEmpty","return_type":"boolean","params":[],"lua_tagged":false},{"name":"isDamaged","return_type":"boolean","params":[],"lua_tagged":false},{"name":"isUndamaged","return_type":"boolean","params":[],"lua_tagged":false},{"name":"allowFrozenItem","return_type":"boolean","params":[],"lua_tagged":false},{"name":"dontAllowFrozenItem","return_type":"boolean","params":[],"lua_tagged":false},{"name":"allowRottenItem","return_type":"boolean","params":[],"lua_tagged":false},{"name":"allowDestroyedItem","return_type":"boolean","params":[],"lua_tagged":false},{"name":"isEmptyContainer","return_type":"boolean","params":[],"lua_tagged":false},{"name":"isWholeFoodItem","return_type":"boolean","params":[],"lua_tagged":false},{"name":"isUncookedFoodItem","return_type":"boolean","params":[],"lua_tagged":false},{"name":"isCookedFoodItem","return_type":"boolean","params":[],"lua_tagged":false},{"name":"isHeadPart","return_type":"boolean","params":[],"lua_tagged":false},{"name":"isSharpenable","return_type":"boolean","params":[],"lua_tagged":false},{"name":"dontPutBack","return_type":"boolean","params":[],"lua_tagged":false},{"name":"inheritColor","return_type":"boolean","params":[],"lua_tagged":false},{"name":"inheritCondition","return_type":"boolean","params":[],"lua_tagged":false},{"name":"inheritHeadCondition","return_type":"boolean","params":[],"lua_tagged":false},{"name":"inheritSharpness","return_type":"boolean","params":[],"lua_tagged":false},{"name":"inheritUses","return_type":"boolean","params":[],"lua_tagged":false},{"name":"isNotDull","return_type":"boolean","params":[],"lua_tagged":false},{"name":"mayDegrade","return_type":"boolean","params":[],"lua_tagged":false},{"name":"mayDegradeLight","return_type":"boolean","params":[],"lua_tagged":false},{"name":"mayDegradeVeryLight","return_type":"boolean","params":[],"lua_tagged":false},{"name":"mayDegradeHeavy","return_type":"boolean","params":[],"lua_tagged":false},{"name":"sharpnessCheck","return_type":"boolean","params":[],"lua_tagged":false},{"name":"getShapedIndex","return_type":"int","params":[],"lua_tagged":false},{"name":"getItemApplyMode","return_type":"ItemApplyMode","params":[],"lua_tagged":false},{"name":"getFluidMatchMode","return_type":"FluidMatchMode","params":[],"lua_tagged":false},{"name":"isFluidExact","return_type":"boolean","params":[],"lua_tagged":false},{"name":"isFluidPrimary","return_type":"boolean","params":[],"lua_tagged":false},{"name":"isFluidMixture","return_type":"boolean","params":[],"lua_tagged":false},{"name":"isFluidAnything","return_type":"boolean","params":[],"lua_tagged":false},{"name":"isVariableAmount","return_type":"boolean","params":[],"lua_tagged":false},{"name":"getIntAmount","return_type":"int","params":[],"lua_tagged":false},{"name":"getAmount","return_type":"float","params":[],"lua_tagged":false},{"name":"getIntMaxAmount","return_type":"int","params":[],"lua_tagged":false},{"name":"getMaxAmount","return_type":"float","params":[],"lua_tagged":false},{"name":"getIntAmount","return_type":"int","params":[{"type":"int","name":"idx"}],"lua_tagged":false},{"name":"getAmount","return_type":"float","params":[{"type":"int","name":"idx"}],"lua_tagged":false},{"name":"getIntMaxAmount","return_type":"int","params":[{"type":"int","name":"idx"}],"lua_tagged":false},{"name":"getMaxAmount","return_type":"float","params":[{"type":"int","name":"idx"}],"lua_tagged":false},{"name":"getIntAmount","return_type":"int","params":[{"type":"String","name":"item"}],"lua_tagged":false},{"name":"getAmount","return_type":"float","params":[{"type":"String","name":"item"}],"lua_tagged":false},{"name":"getIntMaxAmount","return_type":"int","params":[{"type":"String","name":"item"}],"lua_tagged":false},{"name":"getMaxAmount","return_type":"float","params":[{"type":"String","name":"item"}],"lua_tagged":false},{"name":"getRelativeScale","return_type":"float","params":[{"type":"String","name":"item"}],"lua_tagged":false},{"name":"isProp1","return_type":"boolean","params":[],"lua_tagged":false},{"name":"isProp2","return_type":"boolean","params":[],"lua_tagged":false},{"name":"isApplyOnTick","return_type":"boolean","params":[],"lua_tagged":false},{"name":"isAcceptsAnyItem","return_type":"boolean","params":[],"lua_tagged":false},{"name":"isAcceptsAnyFluid","return_type":"boolean","params":[],"lua_tagged":false},{"name":"isAcceptsAnyEnergy","return_type":"boolean","params":[],"lua_tagged":false},{"name":"isHandcraftOnly","return_type":"boolean","params":[],"lua_tagged":false},{"name":"isAutomationOnly","return_type":"boolean","params":[],"lua_tagged":false},{"name":"isReplace","return_type":"boolean","params":[],"lua_tagged":false},{"name":"getReplaceOutputScript","return_type":"OutputScript","params":[],"lua_tagged":false},{"name":"containsItem","return_type":"boolean","params":[{"type":"Item","name":"item"}],"lua_tagged":false},{"name":"containsFluid","return_type":"boolean","params":[{"type":"Fluid","name":"fluid"}],"lua_tagged":false},{"name":"containsEnergy","return_type":"boolean","params":[{"type":"Energy","name":"energy"}],"lua_tagged":false},{"name":"isFluidMatch","return_type":"boolean","params":[{"type":"FluidContainer","name":"container"}],"lua_tagged":false},{"name":"isEnergyMatch","return_type":"boolean","params":[{"type":"DrainableComboItem","name":"item"}],"lua_tagged":false},{"name":"isEnergyMatch","return_type":"boolean","params":[{"type":"Energy","name":"energy"}],"lua_tagged":false},{"name":"OnScriptsLoaded","return_type":"void","params":[{"type":"ScriptLoadMode","name":"loadMode"}],"lua_tagged":false},{"name":"canUseItem","return_type":"boolean","params":[{"type":"InventoryItem","name":"item"},{"type":"IsoGameCharacter","name":"character"}],"lua_tagged":false},{"name":"canUseItem","return_type":"boolean","params":[{"type":"String","name":"item"}],"lua_tagged":false},{"name":"allowFavorites","return_type":"boolean","params":[],"lua_tagged":false},{"name":"passesFavoriteTest","return_type":"boolean","params":[{"type":"InventoryItem","name":"item"}],"lua_tagged":false},{"name":"passesRottenTest","return_type":"boolean","params":[{"type":"InventoryItem","name":"item"}],"lua_tagged":false},{"name":"passesFrozenTest","return_type":"boolean","params":[{"type":"InventoryItem","name":"item"}],"lua_tagged":false},{"name":"passesBrokenTest","return_type":"boolean","params":[{"type":"InventoryItem","name":"item"}],"lua_tagged":false},{"name":"passesSealedTest","return_type":"boolean","params":[{"type":"InventoryItem","name":"item"}],"lua_tagged":false},{"name":"doesItemPassRoutineStatusTests","return_type":"boolean","params":[{"type":"InventoryItem","name":"item"},{"type":"IsoGameCharacter","name":"character"}],"lua_tagged":false},{"name":"doesItemPassClothingTypeStatusTests","return_type":"boolean","params":[{"type":"InventoryItem","name":"item"}],"lua_tagged":false},{"name":"doesItemPassSharpnessStatusTests","return_type":"boolean","params":[{"type":"InventoryItem","name":"item"}],"lua_tagged":false},{"name":"doesItemPassDamageStatusTests","return_type":"boolean","params":[{"type":"InventoryItem","name":"item"}],"lua_tagged":false},{"name":"doesItemPassIsOrNotEmptyAndFullTests","return_type":"boolean","params":[{"type":"InventoryItem","name":"item"}],"lua_tagged":false},{"name":"doesItemPassFoodAndCookingTests","return_type":"boolean","params":[{"type":"InventoryItem","name":"item"}],"lua_tagged":false},{"name":"isCanBeDoneFromFloor","return_type":"boolean","params":[],"lua_tagged":false},{"name":"isRecordInput","return_type":"boolean","params":[],"lua_tagged":false},{"name":"getItemTags","return_type":"Set<ItemTag>","params":[],"lua_tagged":false}],"fields":[],"nested_types":[],"extends":"zombie.scripting.entity.components.crafting.CraftRecipe"}