{"simple_name":"Newspaper","source_file":"zombie/scripting/objects/Newspaper.java","set_exposed":true,"lua_tagged":true,"is_enum":false,"methods":[{"name":"toString","return_type":"String","params":[],"lua_tagged":false},{"name":"getTranslationKey","return_type":"String","params":[],"lua_tagged":false},{"name":"getIssues","return_type":"List<String>","params":[],"lua_tagged":false},{"name":"getTitle","return_type":"String","params":[{"type":"String","name":"title"}],"lua_tagged":false},{"name":"getTranslationInfoKey","return_type":"String","params":[{"type":"String","name":"issue"}],"lua_tagged":false},{"name":"getTranslationTextKey","return_type":"String","params":[{"type":"String","name":"issue"}],"lua_tagged":false}],"fields":[],"nested_types":[]}