{"simple_name":"IsoPlayer","source_file":"zombie/characters/IsoPlayer.java","set_exposed":true,"lua_tagged":true,"is_enum":false,"methods":[{"name":"setOnlineID","return_type":"void","params":[{"type":"short","name":"value"}],"lua_tagged":false},{"name":"getTurnDelta","return_type":"float","params":[],"lua_tagged":false},{"name":"setPerformingAnAction","return_type":"void","params":[{"type":"boolean","name":"val"}],"lua_tagged":false},{"name":"isPerformingAnAction","return_type":"boolean","params":[],"lua_tagged":false},{"name":"isAttacking","return_type":"boolean","params":[],"lua_tagged":false},{"name":"shouldBeTurning","return_type":"boolean","params":[],"lua_tagged":false},{"name":"getIndex","return_type":"int","params":[],"lua_tagged":false},{"name":"TestAnimalSpotPlayer","return_type":"void","params":[{"type":"IsoAnimal","name":"chr"}],"lua_tagged":false},{"name":"TestZombieSpotPlayer","return_type":"void","params":[{"type":"IsoMovingObject","name":"chr"}],"lua_tagged":false},{"name":"getPathSpeed","return_type":"float","params":[],"lua_tagged":false},{"name":"isGhostMode","return_type":"boolean","params":[],"lua_tagged":false},{"name":"setGhostMode","return_type":"void","params":[{"type":"boolean","name":"aGhostMode"},{"type":"boolean","name":"isForced"}],"lua_tagged":false},{"name":"setGhostMode","return_type":"void","params":[{"type":"boolean","name":"aGhostMode"}],"lua_tagged":false},{"name":"isSeeEveryone","return_type":"boolean","params":[],"lua_tagged":false},{"name":"getPlayerMoveDir","return_type":"Vector2","params":[],"lua_tagged":false},{"name":"setPlayerMoveDir","return_type":"void","params":[{"type":"Vector2","name":"aPlayerMoveDir"}],"lua_tagged":false},{"name":"Move","return_type":"void","params":[{"type":"Vector2","name":"dir"}],"lua_tagged":false},{"name":"MoveUnmodded","return_type":"void","params":[{"type":"Vector2","name":"dir"}],"lua_tagged":false},{"name":"nullifyAiming","return_type":"void","params":[],"lua_tagged":false},{"name":"isAimKeyDown","return_type":"boolean","params":[],"lua_tagged":false},{"name":"isAimKeyDownIgnoreMouse","return_type":"boolean","params":[],"lua_tagged":false},{"name":"GetAnimSetName","return_type":"String","params":[],"lua_tagged":false},{"name":"IsInMeleeAttack","return_type":"boolean","params":[],"lua_tagged":false},{"name":"load","return_type":"void","params":[{"type":"ByteBuffer","name":"input"},{"type":"int","name":"worldVersion"},{"type":"boolean","name":"isDebugSave"}],"lua_tagged":false},{"name":"setExtraInfoFlags","return_type":"void","params":[{"type":"byte","name":"flags"},{"type":"boolean","name":"isForced"}],"lua_tagged":false},{"name":"getExtraInfoFlags","return_type":"byte","params":[],"lua_tagged":false},{"name":"getDescription","return_type":"String","params":[{"type":"String","name":"separatorStr"}],"lua_tagged":false},{"name":"save","return_type":"void","params":[{"type":"ByteBuffer","name":"output"},{"type":"boolean","name":"isDebugSave"}],"lua_tagged":false},{"name":"save","return_type":"void","params":[],"lua_tagged":false},{"name":"save","return_type":"void","params":[{"type":"String","name":"fileName"}],"lua_tagged":false},{"name":"load","return_type":"void","params":[{"type":"String","name":"fileName"}],"lua_tagged":false},{"name":"loadChange","return_type":"void","params":[{"type":"IsoObjectChange","name":"change"},{"type":"ByteBufferReader","name":"bb"}],"lua_tagged":false},{"name":"removeFromWorld","return_type":"void","params":[],"lua_tagged":false},{"name":"setVehicle4TestCollision","return_type":"void","params":[{"type":"BaseVehicle","name":"vehicle"}],"lua_tagged":false},{"name":"isSaveFileInUse","return_type":"boolean","params":[],"lua_tagged":false},{"name":"removeSaveFile","return_type":"void","params":[],"lua_tagged":false},{"name":"isSaveFileIPValid","return_type":"boolean","params":[],"lua_tagged":false},{"name":"getObjectName","return_type":"String","params":[],"lua_tagged":false},{"name":"getJoypadBind","return_type":"int","params":[],"lua_tagged":false},{"name":"isLBPressed","return_type":"boolean","params":[],"lua_tagged":false},{"name":"isControllerAimingAxisBeingApplied","return_type":"boolean","params":[],"lua_tagged":false},{"name":"isHeadLookAtControlApplied","return_type":"boolean","params":[],"lua_tagged":false},{"name":"getAimVector","return_type":"Vector2","params":[{"type":"Vector2","name":"vec"}],"lua_tagged":false},{"name":"getGlobalMovementMod","return_type":"float","params":[{"type":"boolean","name":"bDoNoises"}],"lua_tagged":false},{"name":"isInTrees2","return_type":"boolean","params":[{"type":"boolean","name":"ignoreBush"}],"lua_tagged":false},{"name":"getMoveSpeed","return_type":"float","params":[],"lua_tagged":false},{"name":"setMoveSpeed","return_type":"void","params":[{"type":"float","name":"moveSpeed"}],"lua_tagged":false},{"name":"getTorchStrength","return_type":"float","params":[],"lua_tagged":false},{"name":"getInvAimingMod","return_type":"float","params":[],"lua_tagged":false},{"name":"getAimingMod","return_type":"float","params":[],"lua_tagged":false},{"name":"getReloadingMod","return_type":"float","params":[],"lua_tagged":false},{"name":"getAimingRangeMod","return_type":"float","params":[],"lua_tagged":false},{"name":"isPathfindRunning","return_type":"boolean","params":[],"lua_tagged":false},{"name":"setPathfindRunning","return_type":"void","params":[{"type":"boolean","name":"newvalue"}],"lua_tagged":false},{"name":"isBannedAttacking","return_type":"boolean","params":[],"lua_tagged":false},{"name":"setBannedAttacking","return_type":"void","params":[{"type":"boolean","name":"b"}],"lua_tagged":false},{"name":"getInvAimingRangeMod","return_type":"float","params":[],"lua_tagged":false},{"name":"render","return_type":"void","params":[{"type":"float","name":"x"},{"type":"float","name":"y"},{"type":"float","name":"z"},{"type":"ColorInfo","name":"col"},{"type":"boolean","name":"bDoChild"},{"type":"boolean","name":"bWallLightingPass"},{"type":"Shader","name":"shader"}],"lua_tagged":false},{"name":"renderlast","return_type":"void","params":[],"lua_tagged":false},{"name":"onHitByVehicleApplyDamage","return_type":"float","params":[{"type":"BaseVehicle","name":"vehicle"},{"type":"float","name":"impactSpeed"},{"type":"boolean","name":"pushedBack"}],"lua_tagged":false},{"name":"update","return_type":"void","params":[],"lua_tagged":false},{"name":"processWakingUp","return_type":"void","params":[],"lua_tagged":false},{"name":"updateEnduranceWhileSitting","return_type":"void","params":[],"lua_tagged":false},{"name":"updateEnduranceWhileInVehicle","return_type":"void","params":[],"lua_tagged":false},{"name":"postupdate","return_type":"void","params":[],"lua_tagged":false},{"name":"isSolidForSeparate","return_type":"boolean","params":[],"lua_tagged":false},{"name":"isPushableForSeparate","return_type":"boolean","params":[],"lua_tagged":false},{"name":"isPushedByForSeparate","return_type":"boolean","params":[{"type":"IsoMovingObject","name":"other"}],"lua_tagged":false},{"name":"updateMovementRates","return_type":"void","params":[],"lua_tagged":false},{"name":"pressedAttack","return_type":"void","params":[],"lua_tagged":false},{"name":"setAttackVariationX","return_type":"void","params":[{"type":"float","name":"attackVariationX"}],"lua_tagged":false},{"name":"setAttackVariationY","return_type":"void","params":[{"type":"float","name":"attackVariationY"}],"lua_tagged":false},{"name":"canPerformHandToHandCombat","return_type":"boolean","params":[],"lua_tagged":false},{"name":"clearHandToHandAttack","return_type":"void","params":[],"lua_tagged":false},{"name":"setAttackAnimThrowTimer","return_type":"void","params":[{"type":"long","name":"dt"}],"lua_tagged":false},{"name":"isAttackAnimThrowTimeOut","return_type":"boolean","params":[],"lua_tagged":false},{"name":"isAiming","return_type":"boolean","params":[],"lua_tagged":false},{"name":"calculateCritChance","return_type":"int","params":[{"type":"IsoGameCharacter","name":"target"}],"lua_tagged":false},{"name":"isAimControlActive","return_type":"boolean","params":[],"lua_tagged":false},{"name":"isGettingUp","return_type":"boolean","params":[],"lua_tagged":false},{"name":"getMinimumSimulationLevel","return_type":"UpdateSchedulerSimulationLevel","params":[],"lua_tagged":false},{"name":"allowsTwist","return_type":"boolean","params":[],"lua_tagged":false},{"name":"getClosestTo","return_type":"IsoGameCharacter","params":[{"type":"IsoGameCharacter","name":"closestTo"}],"lua_tagged":false},{"name":"hitConsequences","return_type":"void","params":[{"type":"HandWeapon","name":"weapon"},{"type":"IsoGameCharacter","name":"wielder"},{"type":"boolean","name":"bIgnoreDamage"},{"type":"float","name":"damage"},{"type":"boolean","name":"bRemote"}],"lua_tagged":false},{"name":"checkActionGroup","return_type":"void","params":[],"lua_tagged":false},{"name":"getUseableVehicle","return_type":"BaseVehicle","params":[],"lua_tagged":false},{"name":"isNearVehicle","return_type":"Boolean","params":[],"lua_tagged":false},{"name":"getNearVehicle","return_type":"BaseVehicle","params":[],"lua_tagged":false},{"name":"setAngleFromAim","return_type":"void","params":[],"lua_tagged":false},{"name":"calculateContext","return_type":"void","params":[],"lua_tagged":false},{"name":"isSafeToClimbOver","return_type":"boolean","params":[{"type":"IsoDirections","name":"dir"}],"lua_tagged":false},{"name":"doContext","return_type":"boolean","params":[],"lua_tagged":false},{"name":"getContextDoorOrWindowOrWindowFrame","return_type":"IsoObject","params":[{"type":"IsoDirections","name":"assumedDir"}],"lua_tagged":false},{"name":"hopFence","return_type":"boolean","params":[{"type":"IsoDirections","name":"dir"},{"type":"boolean","name":"bTest"}],"lua_tagged":false},{"name":"canClimbOverWall","return_type":"boolean","params":[{"type":"IsoDirections","name":"dir"}],"lua_tagged":false},{"name":"doContextClimbOverWall","return_type":"boolean","params":[{"type":"IsoDirections","name":"dir"}],"lua_tagged":false},{"name":"climbOverWall","return_type":"boolean","params":[{"type":"IsoDirections","name":"dir"}],"lua_tagged":false},{"name":"AttemptAttack","return_type":"boolean","params":[],"lua_tagged":false},{"name":"DoAttack","return_type":"boolean","params":[{"type":"float","name":"chargeDelta"}],"lua_tagged":false},{"name":"DoAttack","return_type":"boolean","params":[{"type":"float","name":"chargeDelta"},{"type":"String","name":"clickSound"}],"lua_tagged":false},{"name":"getPlayerNum","return_type":"int","params":[],"lua_tagged":false},{"name":"updateLOS","return_type":"void","params":[],"lua_tagged":false},{"name":"checkCanSeeClient","return_type":"boolean","params":[{"type":"UdpConnection","name":"remoteConnection"}],"lua_tagged":false},{"name":"checkCanSeeClient","return_type":"boolean","params":[{"type":"IsoPlayer","name":"remoteChr"}],"lua_tagged":false},{"name":"getTimeSurvived","return_type":"String","params":[],"lua_tagged":false},{"name":"IsUsingAimWeapon","return_type":"boolean","params":[],"lua_tagged":false},{"name":"getSleepingPillsTaken","return_type":"int","params":[],"lua_tagged":false},{"name":"setSleepingPillsTaken","return_type":"void","params":[{"type":"int","name":"sleepingPillsTaken"}],"lua_tagged":false},{"name":"resetSleepingPillsTaken","return_type":"void","params":[],"lua_tagged":false},{"name":"isOutside","return_type":"boolean","params":[],"lua_tagged":false},{"name":"getLastSeenZomboidTime","return_type":"double","params":[],"lua_tagged":false},{"name":"getPlayerClothingTemperature","return_type":"float","params":[],"lua_tagged":false},{"name":"getPlayerClothingInsulation","return_type":"float","params":[],"lua_tagged":false},{"name":"getActiveLightItem","return_type":"InventoryItem","params":[],"lua_tagged":false},{"name":"isTorchCone","return_type":"boolean","params":[],"lua_tagged":false},{"name":"getTorchDot","return_type":"float","params":[],"lua_tagged":false},{"name":"getLightDistance","return_type":"float","params":[],"lua_tagged":false},{"name":"pressedMovement","return_type":"boolean","params":[{"type":"boolean","name":"ignoreBlock"}],"lua_tagged":false},{"name":"pressedCancelAction","return_type":"boolean","params":[],"lua_tagged":false},{"name":"checkWalkTo","return_type":"boolean","params":[],"lua_tagged":false},{"name":"pressedAim","return_type":"boolean","params":[],"lua_tagged":false},{"name":"isDoingActionThatCanBeCancelled","return_type":"boolean","params":[],"lua_tagged":false},{"name":"getSteamID","return_type":"long","params":[],"lua_tagged":false},{"name":"setSteamID","return_type":"void","params":[{"type":"long","name":"steamId"}],"lua_tagged":false},{"name":"isTargetedByZombie","return_type":"boolean","params":[],"lua_tagged":false},{"name":"isMaskClicked","return_type":"boolean","params":[{"type":"int","name":"x"},{"type":"int","name":"y"},{"type":"boolean","name":"flip"}],"lua_tagged":false},{"name":"getOffSetXUI","return_type":"int","params":[],"lua_tagged":false},{"name":"setOffSetXUI","return_type":"void","params":[{"type":"int","name":"offSetXUi"}],"lua_tagged":false},{"name":"getOffSetYUI","return_type":"int","params":[],"lua_tagged":false},{"name":"setOffSetYUI","return_type":"void","params":[{"type":"int","name":"offSetYUi"}],"lua_tagged":false},{"name":"getUsername","return_type":"String","params":[],"lua_tagged":false},{"name":"getUsername","return_type":"String","params":[{"type":"Boolean","name":"canShowFirstname"}],"lua_tagged":false},{"name":"getUsername","return_type":"String","params":[{"type":"Boolean","name":"canShowFirstname"},{"type":"Boolean","name":"canShowDisguisedName"}],"lua_tagged":false},{"name":"setUsername","return_type":"void","params":[{"type":"String","name":"newUsername"}],"lua_tagged":false},{"name":"updateUsername","return_type":"void","params":[],"lua_tagged":false},{"name":"getOnlineID","return_type":"short","params":[],"lua_tagged":false},{"name":"isLocalPlayer","return_type":"boolean","params":[],"lua_tagged":false},{"name":"isOnlyPlayerAsleep","return_type":"boolean","params":[],"lua_tagged":false},{"name":"setHasObstacleOnPath","return_type":"void","params":[{"type":"boolean","name":"value"}],"lua_tagged":false},{"name":"isRemoteAndHasObstacleOnPath","return_type":"boolean","params":[],"lua_tagged":false},{"name":"OnDeath","return_type":"void","params":[],"lua_tagged":false},{"name":"isNoClip","return_type":"boolean","params":[],"lua_tagged":false},{"name":"setNoClip","return_type":"void","params":[{"type":"boolean","name":"noClip"},{"type":"boolean","name":"isForced"}],"lua_tagged":false},{"name":"setNoClip","return_type":"void","params":[{"type":"boolean","name":"noClip"}],"lua_tagged":false},{"name":"setAuthorizeMeleeAction","return_type":"void","params":[{"type":"boolean","name":"enabled"}],"lua_tagged":false},{"name":"isAuthorizeMeleeAction","return_type":"boolean","params":[],"lua_tagged":false},{"name":"setAuthorizeShoveStomp","return_type":"void","params":[{"type":"boolean","name":"enabled"}],"lua_tagged":false},{"name":"isAuthorizeShoveStomp","return_type":"boolean","params":[],"lua_tagged":false},{"name":"setAuthorizedHandToHandAction","return_type":"void","params":[{"type":"boolean","name":"enabled"}],"lua_tagged":false},{"name":"isAuthorizedHandToHandAction","return_type":"boolean","params":[],"lua_tagged":false},{"name":"setAuthorizedHandToHand","return_type":"void","params":[{"type":"boolean","name":"enabled"}],"lua_tagged":false},{"name":"isAuthorizedHandToHand","return_type":"boolean","params":[],"lua_tagged":false},{"name":"isBlockMovement","return_type":"boolean","params":[],"lua_tagged":false},{"name":"setBlockMovement","return_type":"void","params":[{"type":"boolean","name":"blockMovement"}],"lua_tagged":false},{"name":"startReceivingBodyDamageUpdates","return_type":"void","params":[{"type":"IsoPlayer","name":"other"}],"lua_tagged":false},{"name":"stopReceivingBodyDamageUpdates","return_type":"void","params":[{"type":"IsoPlayer","name":"other"}],"lua_tagged":false},{"name":"getNutrition","return_type":"Nutrition","params":[],"lua_tagged":false},{"name":"getFitness","return_type":"Fitness","params":[],"lua_tagged":false},{"name":"updateRemotePlayerInVehicle","return_type":"void","params":[],"lua_tagged":false},{"name":"getParameterCharacterMovementSpeed","return_type":"ParameterCharacterMovementSpeed","params":[],"lua_tagged":false},{"name":"setMeleeHitSurface","return_type":"void","params":[{"type":"ParameterMeleeHitSurface.Material","name":"material"}],"lua_tagged":false},{"name":"setMeleeHitSurface","return_type":"void","params":[{"type":"String","name":"material"}],"lua_tagged":false},{"name":"setVehicleHitLocation","return_type":"void","params":[{"type":"BaseVehicle","name":"vehicle"}],"lua_tagged":false},{"name":"DoFootstepSound","return_type":"void","params":[{"type":"String","name":"type"}],"lua_tagged":false},{"name":"playGainExperienceLevelSound","return_type":"long","params":[],"lua_tagged":false},{"name":"playerVoiceSound","return_type":"long","params":[{"type":"String","name":"suffix"}],"lua_tagged":false},{"name":"transmitPlayerVoiceSound","return_type":"long","params":[{"type":"String","name":"suffix"}],"lua_tagged":false},{"name":"stopPlayerVoiceSound","return_type":"long","params":[{"type":"String","name":"suffix"}],"lua_tagged":false},{"name":"updateVocalProperties","return_type":"void","params":[],"lua_tagged":false},{"name":"isPlayingAttackLoopSound","return_type":"boolean","params":[{"type":"String","name":"soundName"}],"lua_tagged":false},{"name":"startAttackLoopSound","return_type":"void","params":[{"type":"String","name":"soundName"}],"lua_tagged":false},{"name":"playBloodSplatterSound","return_type":"void","params":[],"lua_tagged":false},{"name":"setJoypadIgnoreAimUntilCentered","return_type":"void","params":[{"type":"boolean","name":"ignore"}],"lua_tagged":false},{"name":"createPlayerStats","return_type":"ByteBufferWriter","params":[{"type":"ByteBufferWriter","name":"b"},{"type":"String","name":"adminUsername"}],"lua_tagged":false},{"name":"setPlayerStats","return_type":"String","params":[{"type":"ByteBufferReader","name":"bb"},{"type":"String","name":"adminUsername"}],"lua_tagged":false},{"name":"isAllChatMuted","return_type":"boolean","params":[],"lua_tagged":false},{"name":"setAllChatMuted","return_type":"void","params":[{"type":"boolean","name":"allChatMuted"}],"lua_tagged":false},{"name":"getAccessLevel","return_type":"String","params":[],"lua_tagged":false},{"name":"getRole","return_type":"Role","params":[],"lua_tagged":false},{"name":"isAccessLevel","return_type":"boolean","params":[{"type":"String","name":"level"}],"lua_tagged":false},{"name":"setRole","return_type":"void","params":[{"type":"String","name":"newLvl"}],"lua_tagged":false},{"name":"addMechanicsItem","return_type":"void","params":[{"type":"String","name":"itemid"},{"type":"VehiclePart","name":"part"},{"type":"Long","name":"milli"}],"lua_tagged":false},{"name":"getZombieRelevenceScore","return_type":"float","params":[{"type":"IsoZombie","name":"z"}],"lua_tagged":false},{"name":"getVisual","return_type":"BaseVisual","params":[],"lua_tagged":false},{"name":"getHumanVisual","return_type":"HumanVisual","params":[],"lua_tagged":false},{"name":"getAnimalVisual","return_type":"AnimalVisual","params":[],"lua_tagged":false},{"name":"getAnimalType","return_type":"String","params":[],"lua_tagged":false},{"name":"getAnimalSize","return_type":"float","params":[],"lua_tagged":false},{"name":"getItemVisuals","return_type":"ItemVisuals","params":[],"lua_tagged":false},{"name":"getItemVisuals","return_type":"void","params":[{"type":"ItemVisuals","name":"itemVisuals"}],"lua_tagged":false},{"name":"dressInNamedOutfit","return_type":"void","params":[{"type":"String","name":"outfitName"}],"lua_tagged":false},{"name":"dressInClothingItem","return_type":"void","params":[{"type":"String","name":"itemGUID"}],"lua_tagged":false},{"name":"onWornItemsChanged","return_type":"void","params":[],"lua_tagged":false},{"name":"getLastAngle","return_type":"Vector2","params":[],"lua_tagged":false},{"name":"setLastAngle","return_type":"void","params":[{"type":"Vector2","name":"lastAngle"}],"lua_tagged":false},{"name":"getDialogMood","return_type":"int","params":[],"lua_tagged":false},{"name":"setDialogMood","return_type":"void","params":[{"type":"int","name":"dialogMood"}],"lua_tagged":false},{"name":"getPing","return_type":"int","params":[],"lua_tagged":false},{"name":"setPing","return_type":"void","params":[{"type":"int","name":"ping"}],"lua_tagged":false},{"name":"getDragObject","return_type":"IsoMovingObject","params":[],"lua_tagged":false},{"name":"setDragObject","return_type":"void","params":[{"type":"IsoMovingObject","name":"dragObject"}],"lua_tagged":false},{"name":"getAsleepTime","return_type":"float","params":[],"lua_tagged":false},{"name":"setAsleepTime","return_type":"void","params":[{"type":"float","name":"asleepTime"}],"lua_tagged":false},{"name":"getSpottedList","return_type":"Stack<IsoMovingObject>","params":[],"lua_tagged":false},{"name":"getTicksSinceSeenZombie","return_type":"int","params":[],"lua_tagged":false},{"name":"setTicksSinceSeenZombie","return_type":"void","params":[{"type":"int","name":"ticksSinceSeenZombie"}],"lua_tagged":false},{"name":"isWaiting","return_type":"boolean","params":[],"lua_tagged":false},{"name":"setWaiting","return_type":"void","params":[{"type":"boolean","name":"waiting"}],"lua_tagged":false},{"name":"getDragCharacter","return_type":"IsoSurvivor","params":[],"lua_tagged":false},{"name":"setDragCharacter","return_type":"void","params":[{"type":"IsoSurvivor","name":"dragCharacter"}],"lua_tagged":false},{"name":"getHeartDelay","return_type":"float","params":[],"lua_tagged":false},{"name":"setHeartDelay","return_type":"void","params":[{"type":"float","name":"heartDelay"}],"lua_tagged":false},{"name":"getHeartDelayMax","return_type":"float","params":[],"lua_tagged":false},{"name":"setHeartDelayMax","return_type":"void","params":[{"type":"int","name":"heartDelayMax"}],"lua_tagged":false},{"name":"getHoursSurvived","return_type":"double","params":[],"lua_tagged":false},{"name":"setHoursSurvived","return_type":"void","params":[{"type":"double","name":"hrs"}],"lua_tagged":false},{"name":"getMaxWeightDelta","return_type":"float","params":[],"lua_tagged":false},{"name":"setMaxWeightDelta","return_type":"void","params":[{"type":"float","name":"maxWeightDelta"}],"lua_tagged":false},{"name":"isbChangeCharacterDebounce","return_type":"boolean","params":[],"lua_tagged":false},{"name":"setbChangeCharacterDebounce","return_type":"void","params":[{"type":"boolean","name":"changeCharacterDebounce"}],"lua_tagged":false},{"name":"getFollowID","return_type":"int","params":[],"lua_tagged":false},{"name":"setFollowID","return_type":"void","params":[{"type":"int","name":"followId"}],"lua_tagged":false},{"name":"isbSeenThisFrame","return_type":"boolean","params":[],"lua_tagged":false},{"name":"setbSeenThisFrame","return_type":"void","params":[{"type":"boolean","name":"seenThisFrame"}],"lua_tagged":false},{"name":"isbCouldBeSeenThisFrame","return_type":"boolean","params":[],"lua_tagged":false},{"name":"setbCouldBeSeenThisFrame","return_type":"void","params":[{"type":"boolean","name":"couldBeSeenThisFrame"}],"lua_tagged":false},{"name":"getTimeSinceLastStab","return_type":"float","params":[],"lua_tagged":false},{"name":"setTimeSinceLastStab","return_type":"void","params":[{"type":"float","name":"timeSinceLastStab"}],"lua_tagged":false},{"name":"getLastSpotted","return_type":"Stack<IsoMovingObject>","params":[],"lua_tagged":false},{"name":"setLastSpotted","return_type":"void","params":[{"type":"Stack<IsoMovingObject>","name":"lastSpotted"}],"lua_tagged":false},{"name":"getClearSpottedTimer","return_type":"int","params":[],"lua_tagged":false},{"name":"setClearSpottedTimer","return_type":"void","params":[{"type":"int","name":"clearSpottedTimer"}],"lua_tagged":false},{"name":"IsRunning","return_type":"boolean","params":[],"lua_tagged":false},{"name":"InitSpriteParts","return_type":"void","params":[],"lua_tagged":false},{"name":"getTagPrefix","return_type":"String","params":[],"lua_tagged":false},{"name":"setTagPrefix","return_type":"void","params":[{"type":"String","name":"newTag"}],"lua_tagged":false},{"name":"getTagColor","return_type":"ColorInfo","params":[],"lua_tagged":false},{"name":"setTagColor","return_type":"void","params":[{"type":"ColorInfo","name":"tagColor"}],"lua_tagged":false},{"name":"getDisplayName","return_type":"String","params":[],"lua_tagged":false},{"name":"getDisguisedDisplayName","return_type":"String","params":[],"lua_tagged":false},{"name":"resetDisplayName","return_type":"void","params":[],"lua_tagged":false},{"name":"setDisplayName","return_type":"void","params":[{"type":"String","name":"displayName"}],"lua_tagged":false},{"name":"isSeeNonPvpZone","return_type":"boolean","params":[],"lua_tagged":false},{"name":"isSeeDesignationZone","return_type":"boolean","params":[],"lua_tagged":false},{"name":"setSeeDesignationZone","return_type":"void","params":[{"type":"boolean","name":"seeMetaAnimalZone"}],"lua_tagged":false},{"name":"addSelectedZoneForHighlight","return_type":"void","params":[{"type":"Double","name":"id"}],"lua_tagged":false},{"name":"setSelectedZoneForHighlight","return_type":"void","params":[{"type":"Double","name":"id"}],"lua_tagged":false},{"name":"getSelectedZoneForHighlight","return_type":"Double","params":[],"lua_tagged":false},{"name":"getSelectedZonesForHighlight","return_type":"ArrayList<Double>","params":[],"lua_tagged":false},{"name":"resetSelectedZonesForHighlight","return_type":"void","params":[],"lua_tagged":false},{"name":"setSeeNonPvpZone","return_type":"void","params":[{"type":"boolean","name":"seeNonPvpZone"}],"lua_tagged":false},{"name":"checkZonesInterception","return_type":"boolean","params":[{"type":"int","name":"x1"},{"type":"int","name":"x2"},{"type":"int","name":"y1"},{"type":"int","name":"y2"}],"lua_tagged":false},{"name":"isShowTag","return_type":"boolean","params":[],"lua_tagged":false},{"name":"setShowTag","return_type":"void","params":[{"type":"boolean","name":"show"}],"lua_tagged":false},{"name":"isFactionPvp","return_type":"boolean","params":[],"lua_tagged":false},{"name":"setFactionPvp","return_type":"void","params":[{"type":"boolean","name":"pvp"}],"lua_tagged":false},{"name":"isForceAim","return_type":"boolean","params":[],"lua_tagged":false},{"name":"setForceAim","return_type":"void","params":[{"type":"boolean","name":"forceAim"}],"lua_tagged":false},{"name":"toggleForceAim","return_type":"boolean","params":[],"lua_tagged":false},{"name":"isForceSprint","return_type":"boolean","params":[],"lua_tagged":false},{"name":"setForceSprint","return_type":"void","params":[{"type":"boolean","name":"forceSprint"}],"lua_tagged":false},{"name":"toggleForceSprint","return_type":"boolean","params":[],"lua_tagged":false},{"name":"isForceRun","return_type":"boolean","params":[],"lua_tagged":false},{"name":"setForceRun","return_type":"void","params":[{"type":"boolean","name":"forceRun"}],"lua_tagged":false},{"name":"toggleForceRun","return_type":"boolean","params":[],"lua_tagged":false},{"name":"isForceOverrideAnim","return_type":"boolean","params":[],"lua_tagged":false},{"name":"setForceOverrideAnim","return_type":"void","params":[{"type":"boolean","name":"forceOverride"}],"lua_tagged":false},{"name":"getMechanicsItem","return_type":"Long","params":[{"type":"String","name":"itemId"}],"lua_tagged":false},{"name":"isWearingNightVisionGoggles","return_type":"boolean","params":[],"lua_tagged":false},{"name":"setWearingNightVisionGoggles","return_type":"void","params":[{"type":"boolean","name":"b"}],"lua_tagged":false},{"name":"OnAnimEvent","return_type":"void","params":[{"type":"AnimLayer","name":"sender"},{"type":"AnimationTrack","name":"track"},{"type":"AnimEvent","name":"event"}],"lua_tagged":false},{"name":"setAddedToModelManager","return_type":"void","params":[{"type":"ModelManager","name":"modelManager"},{"type":"boolean","name":"isAdded"}],"lua_tagged":false},{"name":"isTimedActionInstant","return_type":"boolean","params":[],"lua_tagged":false},{"name":"isSkeleton","return_type":"boolean","params":[],"lua_tagged":false},{"name":"addWorldSoundUnlessInvisible","return_type":"void","params":[{"type":"int","name":"radius"},{"type":"int","name":"volume"},{"type":"boolean","name":"bStressHumans"}],"lua_tagged":false},{"name":"getMoodleLevel","return_type":"int","params":[{"type":"MoodleType","name":"type"}],"lua_tagged":false},{"name":"isAttackStarted","return_type":"boolean","params":[],"lua_tagged":false},{"name":"setAttackStarted","return_type":"void","params":[{"type":"boolean","name":"attackStarted"}],"lua_tagged":false},{"name":"isBehaviourMoving","return_type":"boolean","params":[],"lua_tagged":false},{"name":"isJustMoved","return_type":"boolean","params":[],"lua_tagged":false},{"name":"setJustMoved","return_type":"void","params":[{"type":"boolean","name":"val"}],"lua_tagged":false},{"name":"isPlayerMoving","return_type":"boolean","params":[],"lua_tagged":false},{"name":"getTimedActionTimeModifier","return_type":"float","params":[],"lua_tagged":false},{"name":"isLookingWhileInVehicle","return_type":"boolean","params":[],"lua_tagged":false},{"name":"setInitiateAttack","return_type":"void","params":[{"type":"boolean","name":"initiate"}],"lua_tagged":false},{"name":"isInitiateAttack","return_type":"boolean","params":[],"lua_tagged":false},{"name":"isIgnoreInputsForDirection","return_type":"boolean","params":[],"lua_tagged":false},{"name":"setIgnoreInputsForDirection","return_type":"void","params":[{"type":"boolean","name":"ignoreInputsForDirection"}],"lua_tagged":false},{"name":"isIgnoreContextKey","return_type":"boolean","params":[],"lua_tagged":false},{"name":"setIgnoreContextKey","return_type":"void","params":[{"type":"boolean","name":"ignoreContextKey"}],"lua_tagged":false},{"name":"isIgnoreAutoVault","return_type":"boolean","params":[],"lua_tagged":false},{"name":"setIgnoreAutoVault","return_type":"void","params":[{"type":"boolean","name":"ignoreAutoVault"}],"lua_tagged":false},{"name":"isAllowSprint","return_type":"boolean","params":[],"lua_tagged":false},{"name":"setAllowSprint","return_type":"void","params":[{"type":"boolean","name":"allowSprint"}],"lua_tagged":false},{"name":"isAllowRun","return_type":"boolean","params":[],"lua_tagged":false},{"name":"setAllowRun","return_type":"void","params":[{"type":"boolean","name":"allowRun"}],"lua_tagged":false},{"name":"isAttackType","return_type":"boolean","params":[{"type":"AttackType","name":"attackType"}],"lua_tagged":false},{"name":"getAttackType","return_type":"AttackType","params":[],"lua_tagged":false},{"name":"setAttackType","return_type":"void","params":[{"type":"AttackType","name":"attackType"}],"lua_tagged":false},{"name":"canSeeAll","return_type":"boolean","params":[],"lua_tagged":false},{"name":"setCanSeeAll","return_type":"void","params":[{"type":"boolean","name":"b"}],"lua_tagged":false},{"name":"isCheatPlayerSeeEveryone","return_type":"boolean","params":[],"lua_tagged":false},{"name":"getRelevantAndDistance","return_type":"float","params":[{"type":"float","name":"x"},{"type":"float","name":"y"},{"type":"float","name":"relevantRange"}],"lua_tagged":false},{"name":"canHearAll","return_type":"boolean","params":[],"lua_tagged":false},{"name":"setCanHearAll","return_type":"void","params":[{"type":"boolean","name":"b"}],"lua_tagged":false},{"name":"getAlreadyReadBook","return_type":"ArrayList<String>","params":[],"lua_tagged":false},{"name":"setMoodleCantSprint","return_type":"void","params":[{"type":"boolean","name":"b"}],"lua_tagged":false},{"name":"setAttackFromBehind","return_type":"void","params":[{"type":"boolean","name":"attackFromBehind"}],"lua_tagged":false},{"name":"isAttackFromBehind","return_type":"boolean","params":[],"lua_tagged":false},{"name":"getDamageFromHitByACar","return_type":"float","params":[{"type":"float","name":"vehicleSpeed"}],"lua_tagged":false},{"name":"Kill","return_type":"void","params":[{"type":"IsoGameCharacter","name":"killer"}],"lua_tagged":false},{"name":"becomeCorpse","return_type":"IsoDeadBody","params":[],"lua_tagged":false},{"name":"preupdate","return_type":"void","params":[],"lua_tagged":false},{"name":"getHitReactionNetworkAI","return_type":"HitReactionNetworkAI","params":[],"lua_tagged":false},{"name":"getNetworkCharacterAI","return_type":"NetworkCharacterAI","params":[],"lua_tagged":false},{"name":"setFishingStage","return_type":"void","params":[{"type":"String","name":"stage"}],"lua_tagged":false},{"name":"setFitnessSpeed","return_type":"void","params":[],"lua_tagged":false},{"name":"isLocal","return_type":"boolean","params":[],"lua_tagged":false},{"name":"isClimbOverWallSuccess","return_type":"boolean","params":[],"lua_tagged":false},{"name":"setClimbOverWallSuccess","return_type":"void","params":[{"type":"boolean","name":"climbOverWallSuccess"}],"lua_tagged":false},{"name":"isClimbOverWallStruggle","return_type":"boolean","params":[],"lua_tagged":false},{"name":"setClimbOverWallStruggle","return_type":"void","params":[{"type":"boolean","name":"climbOverWallStruggle"}],"lua_tagged":false},{"name":"isSkipResolveCollision","return_type":"boolean","params":[],"lua_tagged":false},{"name":"isShowMPInfos","return_type":"boolean","params":[],"lua_tagged":false},{"name":"setShowMPInfos","return_type":"void","params":[{"type":"boolean","name":"b"}],"lua_tagged":false},{"name":"getMusicIntensityEvents","return_type":"MusicIntensityEvents","params":[],"lua_tagged":false},{"name":"triggerMusicIntensityEvent","return_type":"void","params":[{"type":"String","name":"id"}],"lua_tagged":false},{"name":"getMusicThreatStatuses","return_type":"MusicThreatStatuses","params":[],"lua_tagged":false},{"name":"addAttachedAnimal","return_type":"void","params":[{"type":"IsoAnimal","name":"anim"}],"lua_tagged":false},{"name":"getAttachedAnimals","return_type":"ArrayList<IsoAnimal>","params":[],"lua_tagged":false},{"name":"removeAttachedAnimal","return_type":"void","params":[{"type":"IsoAnimal","name":"animal"}],"lua_tagged":false},{"name":"removeAllAttachedAnimals","return_type":"void","params":[],"lua_tagged":false},{"name":"lureAnimal","return_type":"void","params":[{"type":"InventoryItem","name":"item"}],"lua_tagged":false},{"name":"getLuredAnimals","return_type":"ArrayList<IsoAnimal>","params":[],"lua_tagged":false},{"name":"stopLuringAnimals","return_type":"void","params":[{"type":"boolean","name":"eatFood"}],"lua_tagged":false},{"name":"setIsLuringAnimals","return_type":"void","params":[{"type":"boolean","name":"luring"}],"lua_tagged":false},{"name":"getVoiceType","return_type":"int","params":[],"lua_tagged":false},{"name":"setVoiceType","return_type":"void","params":[{"type":"int","name":"voiceType"}],"lua_tagged":false},{"name":"setVoicePitch","return_type":"void","params":[{"type":"float","name":"voicePitch"}],"lua_tagged":false},{"name":"isFarming","return_type":"boolean","params":[],"lua_tagged":false},{"name":"setIsFarming","return_type":"void","params":[{"type":"boolean","name":"isFarmingBool"}],"lua_tagged":false},{"name":"tooDarkToRead","return_type":"boolean","params":[],"lua_tagged":false},{"name":"isWalking","return_type":"boolean","params":[],"lua_tagged":false},{"name":"isInvPageDirty","return_type":"boolean","params":[],"lua_tagged":false},{"name":"setInvPageDirty","return_type":"void","params":[{"type":"boolean","name":"b"}],"lua_tagged":false},{"name":"getVoicePitch","return_type":"float","params":[],"lua_tagged":false},{"name":"setCombatSpeed","return_type":"void","params":[{"type":"float","name":"combatSpeed"}],"lua_tagged":false},{"name":"getCombatSpeed","return_type":"float","params":[],"lua_tagged":false},{"name":"isMeleePressed","return_type":"boolean","params":[],"lua_tagged":false},{"name":"isGrapplePressed","return_type":"boolean","params":[],"lua_tagged":false},{"name":"setRole","return_type":"void","params":[{"type":"Role","name":"newRole"}],"lua_tagged":false},{"name":"wasLastAttackHandToHand","return_type":"boolean","params":[],"lua_tagged":false},{"name":"setLastAttackWasHandToHand","return_type":"void","params":[{"type":"boolean","name":"lastAttackWasHandToHand"}],"lua_tagged":false},{"name":"petAnimal","return_type":"void","params":[],"lua_tagged":false},{"name":"getUseableAnimal","return_type":"IsoAnimal","params":[],"lua_tagged":false},{"name":"getTimedActionToRetrigger","return_type":"LuaTimedActionNew","params":[],"lua_tagged":false},{"name":"setTimedActionToRetrigger","return_type":"void","params":[{"type":"LuaTimedActionNew","name":"timedActionToRetrigger"}],"lua_tagged":false},{"name":"getPlayerCraftHistory","return_type":"PlayerCraftHistory","params":[],"lua_tagged":false},{"name":"isFavouriteRecipe","return_type":"boolean","params":[{"type":"String","name":"recipe"}],"lua_tagged":false},{"name":"isFavouriteRecipe","return_type":"boolean","params":[{"type":"CraftRecipe","name":"recipe"}],"lua_tagged":false},{"name":"isUnwanted","return_type":"boolean","params":[{"type":"String","name":"item"}],"lua_tagged":false},{"name":"setUnwanted","return_type":"void","params":[{"type":"String","name":"item"},{"type":"Boolean","name":"unwanted"}],"lua_tagged":false},{"name":"getTimeSinceLastNetData","return_type":"int","params":[],"lua_tagged":false},{"name":"setTimeSinceLastNetData","return_type":"void","params":[{"type":"int","name":"timeSinceLastNetData"}],"lua_tagged":false},{"name":"getLastRemoteUpdate","return_type":"long","params":[],"lua_tagged":false},{"name":"setLastRemoteUpdate","return_type":"void","params":[{"type":"long","name":"lastRemoteUpdate"}],"lua_tagged":false},{"name":"getAutoDrink","return_type":"boolean","params":[],"lua_tagged":false},{"name":"setAutoDrink","return_type":"void","params":[{"type":"boolean","name":"autoDrink"}],"lua_tagged":false}],"fields":[{"name":"physicsDebugRenderer","type":"PhysicsDebugRenderer","lua_tagged":false},{"name":"remoteSneakLvl","type":"int","lua_tagged":false},{"name":"remoteStrLvl","type":"int","lua_tagged":false},{"name":"remoteFitLvl","type":"int","lua_tagged":false},{"name":"moodleCantSprint","type":"boolean","lua_tagged":false},{"name":"luredAnimals","type":"ArrayList<IsoAnimal>","lua_tagged":false},{"name":"isLuringAnimals","type":"boolean","lua_tagged":false},{"name":"spottedByPlayer","type":"boolean","lua_tagged":false},{"name":"targetedByZombie","type":"boolean","lua_tagged":false},{"name":"lastTargeted","type":"float","lua_tagged":false},{"name":"timeSinceOpenDoor","type":"float","lua_tagged":false},{"name":"timeSinceCloseDoor","type":"float","lua_tagged":false},{"name":"remote","type":"boolean","lua_tagged":false},{"name":"role","type":"Role","lua_tagged":false},{"name":"tagPrefix","type":"String","lua_tagged":false},{"name":"showTag","type":"boolean","lua_tagged":false},{"name":"factionPvp","type":"boolean","lua_tagged":false},{"name":"onlineId","type":"short","lua_tagged":false},{"name":"onlineChunkGridWidth","type":"int","lua_tagged":false},{"name":"joypadMovementActive","type":"boolean","lua_tagged":false},{"name":"joypadIgnoreAimUntilCentered","type":"boolean","lua_tagged":false},{"name":"joypadIgnoreChargingRt","type":"boolean","lua_tagged":false},{"name":"mpTorchCone","type":"boolean","lua_tagged":false},{"name":"mpTorchDist","type":"float","lua_tagged":false},{"name":"mpTorchStrength","type":"float","lua_tagged":false},{"name":"playerIndex","type":"int","lua_tagged":false},{"name":"serverPlayerIndex","type":"int","lua_tagged":false},{"name":"useChargeDelta","type":"float","lua_tagged":false},{"name":"joypadBind","type":"int","lua_tagged":false},{"name":"contextPanic","type":"float","lua_tagged":false},{"name":"numNearbyBuildingsRooms","type":"float","lua_tagged":false},{"name":"isCharging","type":"boolean","lua_tagged":false},{"name":"isChargingLt","type":"boolean","lua_tagged":false},{"name":"maxWeightDelta","type":"float","lua_tagged":false},{"name":"currentSpeed","type":"float","lua_tagged":false},{"name":"deathFinished","type":"boolean","lua_tagged":false},{"name":"isSpeek","type":"boolean","lua_tagged":false},{"name":"isVoiceMute","type":"boolean","lua_tagged":false},{"name":"playerMoveDir","type":"Vector2","lua_tagged":false},{"name":"soundListener","type":"BaseSoundListener","lua_tagged":false},{"name":"username","type":"String","lua_tagged":false},{"name":"dirtyRecalcGridStack","type":"boolean","lua_tagged":false},{"name":"dirtyRecalcGridStackTime","type":"float","lua_tagged":false},{"name":"runningTime","type":"float","lua_tagged":false},{"name":"timePressedContext","type":"float","lua_tagged":false},{"name":"chargeTime","type":"float","lua_tagged":false},{"name":"closestZombie","type":"float","lua_tagged":false},{"name":"lastAngle","type":"Vector2","lua_tagged":false},{"name":"saveFileName","type":"String","lua_tagged":false},{"name":"bannedAttacking","type":"boolean","lua_tagged":false},{"name":"sqlId","type":"int","lua_tagged":false},{"name":"bleedingLevel","type":"byte","lua_tagged":false},{"name":"networkAi","type":"NetworkPlayerAI","lua_tagged":false},{"name":"accessLevel","type":"String","lua_tagged":false},{"name":"autoDrink","type":"boolean","lua_tagged":false}],"nested_types":[{"name":"InputState","kind":"class","fqn":"zombie.characters.IsoPlayer.InputState"},{"name":"VehicleContainerData","kind":"class","fqn":"zombie.characters.IsoPlayer.VehicleContainerData"},{"name":"GrapplerGruntChance","kind":"class","fqn":"zombie.characters.IsoPlayer.GrapplerGruntChance"},{"name":"MoveVars","kind":"class","fqn":"zombie.characters.IsoPlayer.MoveVars"},{"name":"s_performance","kind":"class","fqn":"zombie.characters.IsoPlayer.s_performance"},{"name":"VehicleContainer","kind":"class","fqn":"zombie.characters.IsoPlayer.VehicleContainer"}],"extends":"zombie.characters.IsoLivingCharacter","implements":["zombie.core.skinnedmodel.visual.IAnimalVisual","zombie.core.skinnedmodel.visual.IHumanVisual","zombie.network.fields.IPositional"],"subclasses":["zombie.characters.animals.IsoAnimal"]}