{"simple_name":"MainScreenState","source_file":"zombie/gameStates/MainScreenState.java","set_exposed":true,"lua_tagged":true,"is_enum":false,"methods":[{"name":"enter","return_type":"void","params":[],"lua_tagged":false},{"name":"ShouldShowLogo","return_type":"boolean","params":[],"lua_tagged":false},{"name":"exit","return_type":"void","params":[],"lua_tagged":false},{"name":"render","return_type":"void","params":[],"lua_tagged":false},{"name":"renderBackground","return_type":"void","params":[],"lua_tagged":false},{"name":"update","return_type":"GameStateMachine.StateAction","params":[],"lua_tagged":false},{"name":"setConnectToServerState","return_type":"void","params":[{"type":"ConnectToServerState","name":"state"}],"lua_tagged":false}],"fields":[{"name":"alpha","type":"float","lua_tagged":false},{"name":"alphaStep","type":"float","lua_tagged":false},{"name":"elements","type":"ArrayList<ScreenElement>","lua_tagged":false},{"name":"targetAlpha","type":"float","lua_tagged":false},{"name":"showLogo","type":"boolean","lua_tagged":false},{"name":"lightningTimelineMarker","type":"boolean","lua_tagged":false},{"name":"worldMap","type":"UIWorldMap","lua_tagged":false},{"name":"lightningDelta","type":"float","lua_tagged":false},{"name":"lightningTargetDelta","type":"float","lua_tagged":false},{"name":"lightningFullTimer","type":"float","lua_tagged":false},{"name":"lightningCount","type":"float","lua_tagged":false},{"name":"lightOffCount","type":"float","lua_tagged":false}],"nested_types":[{"name":"ScreenElement","kind":"class","fqn":"zombie.gameStates.MainScreenState.ScreenElement"},{"name":"Credit","kind":"class","fqn":"zombie.gameStates.MainScreenState.Credit"}],"extends":"zombie.gameStates.GameState"}