{"simple_name":"GameSound","source_file":"zombie/audio/GameSound.java","set_exposed":true,"lua_tagged":true,"is_enum":false,"methods":[{"name":"getName","return_type":"String","params":[],"lua_tagged":false},{"name":"getCategory","return_type":"String","params":[],"lua_tagged":false},{"name":"isLooped","return_type":"boolean","params":[],"lua_tagged":false},{"name":"setUserVolume","return_type":"void","params":[{"type":"float","name":"gain"}],"lua_tagged":false},{"name":"getUserVolume","return_type":"float","params":[],"lua_tagged":false},{"name":"getRandomClip","return_type":"GameSoundClip","params":[],"lua_tagged":false},{"name":"getMasterName","return_type":"String","params":[],"lua_tagged":false},{"name":"numClipsUsingParameter","return_type":"int","params":[{"type":"String","name":"parameterName"}],"lua_tagged":false},{"name":"reset","return_type":"void","params":[],"lua_tagged":false}],"fields":[{"name":"name","type":"String","lua_tagged":false},{"name":"category","type":"String","lua_tagged":false},{"name":"loop","type":"boolean","lua_tagged":false},{"name":"is3d","type":"boolean","lua_tagged":false},{"name":"clips","type":"ArrayList<GameSoundClip>","lua_tagged":false},{"name":"master","type":"MasterVolume","lua_tagged":false},{"name":"maxInstancesPerEmitter","type":"int","lua_tagged":false},{"name":"reloadEpoch","type":"short","lua_tagged":false}],"nested_types":[{"name":"MasterVolume","kind":"enum","fqn":"zombie.audio.GameSound.MasterVolume"}]}